<profile>

<ReportVersion>
<Version>2023.2</Version>
</ReportVersion>

<UserAssignments>
<unit>ns</unit>
<ProductFamily>zynquplus</ProductFamily>
<Part>xck26-sfvc784-2LV-c</Part>
<TopModelName>normalize_array_ap_fixed_16u_array_ap_fixed_33_21_5_3_0_16u_config9_s</TopModelName>
<TargetClockPeriod>5.00</TargetClockPeriod>
<ClockUncertainty>1.35</ClockUncertainty>
<FlowTarget>vivado</FlowTarget>
</UserAssignments>

<PerformanceEstimates>
<PipelineType>no</PipelineType>
<SummaryOfTimingAnalysis>
<unit>ns</unit>
<EstimatedClockPeriod>2.831</EstimatedClockPeriod>
</SummaryOfTimingAnalysis>
<SummaryOfOverallLatency>
<unit>clock cycles</unit>
<Best-caseLatency>704</Best-caseLatency>
<Average-caseLatency>704</Average-caseLatency>
<Worst-caseLatency>704</Worst-caseLatency>
<Best-caseRealTimeLatency>3.520 us</Best-caseRealTimeLatency>
<Average-caseRealTimeLatency>3.520 us</Average-caseRealTimeLatency>
<Worst-caseRealTimeLatency>3.520 us</Worst-caseRealTimeLatency>
<Interval-min>704</Interval-min>
<Interval-max>704</Interval-max>
</SummaryOfOverallLatency>
<SummaryOfLoopLatency>
<BatchNormLoop>
<Slack>3.65</Slack>
<TripCount>700</TripCount>
<Latency>702</Latency>
<AbsoluteTimeLatency>3510</AbsoluteTimeLatency>
<PipelineII>1</PipelineII>
<PipelineDepth>4</PipelineDepth>
<InstanceList>
</InstanceList>
</BatchNormLoop>
</SummaryOfLoopLatency>
<SummaryOfViolations>
<IssueType>-</IssueType>
<ViolationType>-</ViolationType>
<SourceLocation>firmware/nnet_utils/nnet_batchnorm_stream.h:25</SourceLocation>
<SummaryOfLoopViolations>
<BatchNormLoop>
<Name>BatchNormLoop</Name>
<IssueType>-</IssueType>
<ViolationType>-</ViolationType>
<SourceLocation>firmware/nnet_utils/nnet_batchnorm_stream.h:25</SourceLocation>
</BatchNormLoop>
</SummaryOfLoopViolations>
</SummaryOfViolations>
</PerformanceEstimates>

<AreaEstimates>
<Resources>
<DSP>16</DSP>
<FF>716</FF>
<LUT>737</LUT>
<BRAM_18K>0</BRAM_18K>
<URAM>0</URAM>
</Resources>
<AvailableResources>
<BRAM_18K>288</BRAM_18K>
<DSP>1248</DSP>
<FF>234240</FF>
<LUT>117120</LUT>
<URAM>64</URAM>
</AvailableResources>
</AreaEstimates>

<InterfaceSummary>
<RtlPorts>
<name>ap_clk</name>
<Object>normalize&lt;array&lt;ap_fixed,16u&gt;,array&lt;ap_fixed&lt;33,21,5,3,0&gt;,16u&gt;,config9&gt;</Object>
<Type>return value</Type>
<Scope></Scope>
<IOProtocol>ap_ctrl_hs</IOProtocol>
<IOConfig></IOConfig>
<Dir>in</Dir>
<Bits>1</Bits>
<Attribute>control</Attribute>
</RtlPorts>
<RtlPorts>
<name>ap_rst</name>
<Object>normalize&lt;array&lt;ap_fixed,16u&gt;,array&lt;ap_fixed&lt;33,21,5,3,0&gt;,16u&gt;,config9&gt;</Object>
<Type>return value</Type>
<Scope></Scope>
<IOProtocol>ap_ctrl_hs</IOProtocol>
<IOConfig></IOConfig>
<Dir>in</Dir>
<Bits>1</Bits>
<Attribute>control</Attribute>
</RtlPorts>
<RtlPorts>
<name>ap_start</name>
<Object>normalize&lt;array&lt;ap_fixed,16u&gt;,array&lt;ap_fixed&lt;33,21,5,3,0&gt;,16u&gt;,config9&gt;</Object>
<Type>return value</Type>
<Scope></Scope>
<IOProtocol>ap_ctrl_hs</IOProtocol>
<IOConfig></IOConfig>
<Dir>in</Dir>
<Bits>1</Bits>
<Attribute>control</Attribute>
</RtlPorts>
<RtlPorts>
<name>start_full_n</name>
<Object>normalize&lt;array&lt;ap_fixed,16u&gt;,array&lt;ap_fixed&lt;33,21,5,3,0&gt;,16u&gt;,config9&gt;</Object>
<Type>return value</Type>
<Scope></Scope>
<IOProtocol>ap_ctrl_hs</IOProtocol>
<IOConfig></IOConfig>
<Dir>in</Dir>
<Bits>1</Bits>
<Attribute>unknown</Attribute>
</RtlPorts>
<RtlPorts>
<name>ap_done</name>
<Object>normalize&lt;array&lt;ap_fixed,16u&gt;,array&lt;ap_fixed&lt;33,21,5,3,0&gt;,16u&gt;,config9&gt;</Object>
<Type>return value</Type>
<Scope></Scope>
<IOProtocol>ap_ctrl_hs</IOProtocol>
<IOConfig></IOConfig>
<Dir>out</Dir>
<Bits>1</Bits>
<Attribute>control</Attribute>
</RtlPorts>
<RtlPorts>
<name>ap_continue</name>
<Object>normalize&lt;array&lt;ap_fixed,16u&gt;,array&lt;ap_fixed&lt;33,21,5,3,0&gt;,16u&gt;,config9&gt;</Object>
<Type>return value</Type>
<Scope></Scope>
<IOProtocol>ap_ctrl_hs</IOProtocol>
<IOConfig></IOConfig>
<Dir>in</Dir>
<Bits>1</Bits>
<Attribute>control</Attribute>
</RtlPorts>
<RtlPorts>
<name>ap_idle</name>
<Object>normalize&lt;array&lt;ap_fixed,16u&gt;,array&lt;ap_fixed&lt;33,21,5,3,0&gt;,16u&gt;,config9&gt;</Object>
<Type>return value</Type>
<Scope></Scope>
<IOProtocol>ap_ctrl_hs</IOProtocol>
<IOConfig></IOConfig>
<Dir>out</Dir>
<Bits>1</Bits>
<Attribute>control</Attribute>
</RtlPorts>
<RtlPorts>
<name>ap_ready</name>
<Object>normalize&lt;array&lt;ap_fixed,16u&gt;,array&lt;ap_fixed&lt;33,21,5,3,0&gt;,16u&gt;,config9&gt;</Object>
<Type>return value</Type>
<Scope></Scope>
<IOProtocol>ap_ctrl_hs</IOProtocol>
<IOConfig></IOConfig>
<Dir>out</Dir>
<Bits>1</Bits>
<Attribute>control</Attribute>
</RtlPorts>
<RtlPorts>
<name>start_out</name>
<Object>normalize&lt;array&lt;ap_fixed,16u&gt;,array&lt;ap_fixed&lt;33,21,5,3,0&gt;,16u&gt;,config9&gt;</Object>
<Type>return value</Type>
<Scope></Scope>
<IOProtocol>ap_ctrl_hs</IOProtocol>
<IOConfig></IOConfig>
<Dir>out</Dir>
<Bits>1</Bits>
<Attribute>unknown</Attribute>
</RtlPorts>
<RtlPorts>
<name>start_write</name>
<Object>normalize&lt;array&lt;ap_fixed,16u&gt;,array&lt;ap_fixed&lt;33,21,5,3,0&gt;,16u&gt;,config9&gt;</Object>
<Type>return value</Type>
<Scope></Scope>
<IOProtocol>ap_ctrl_hs</IOProtocol>
<IOConfig></IOConfig>
<Dir>out</Dir>
<Bits>1</Bits>
<Attribute>unknown</Attribute>
</RtlPorts>
<RtlPorts>
<name>layer7_out_dout</name>
<Object>layer7_out</Object>
<Type>pointer</Type>
<Scope></Scope>
<IOProtocol>ap_fifo</IOProtocol>
<IOConfig></IOConfig>
<Dir>in</Dir>
<Bits>256</Bits>
<Attribute>control</Attribute>
</RtlPorts>
<RtlPorts>
<name>layer7_out_num_data_valid</name>
<Object>layer7_out</Object>
<Type>pointer</Type>
<Scope></Scope>
<IOProtocol>ap_fifo</IOProtocol>
<IOConfig></IOConfig>
<Dir>in</Dir>
<Bits>11</Bits>
<Attribute>control</Attribute>
</RtlPorts>
<RtlPorts>
<name>layer7_out_fifo_cap</name>
<Object>layer7_out</Object>
<Type>pointer</Type>
<Scope></Scope>
<IOProtocol>ap_fifo</IOProtocol>
<IOConfig></IOConfig>
<Dir>in</Dir>
<Bits>11</Bits>
<Attribute>unknown</Attribute>
</RtlPorts>
<RtlPorts>
<name>layer7_out_empty_n</name>
<Object>layer7_out</Object>
<Type>pointer</Type>
<Scope></Scope>
<IOProtocol>ap_fifo</IOProtocol>
<IOConfig></IOConfig>
<Dir>in</Dir>
<Bits>1</Bits>
<Attribute>control</Attribute>
</RtlPorts>
<RtlPorts>
<name>layer7_out_read</name>
<Object>layer7_out</Object>
<Type>pointer</Type>
<Scope></Scope>
<IOProtocol>ap_fifo</IOProtocol>
<IOConfig></IOConfig>
<Dir>out</Dir>
<Bits>1</Bits>
<Attribute>control</Attribute>
</RtlPorts>
<RtlPorts>
<name>layer9_out_din</name>
<Object>layer9_out</Object>
<Type>pointer</Type>
<Scope></Scope>
<IOProtocol>ap_fifo</IOProtocol>
<IOConfig></IOConfig>
<Dir>out</Dir>
<Bits>528</Bits>
<Attribute>control</Attribute>
</RtlPorts>
<RtlPorts>
<name>layer9_out_num_data_valid</name>
<Object>layer9_out</Object>
<Type>pointer</Type>
<Scope></Scope>
<IOProtocol>ap_fifo</IOProtocol>
<IOConfig></IOConfig>
<Dir>in</Dir>
<Bits>11</Bits>
<Attribute>control</Attribute>
</RtlPorts>
<RtlPorts>
<name>layer9_out_fifo_cap</name>
<Object>layer9_out</Object>
<Type>pointer</Type>
<Scope></Scope>
<IOProtocol>ap_fifo</IOProtocol>
<IOConfig></IOConfig>
<Dir>in</Dir>
<Bits>11</Bits>
<Attribute>unknown</Attribute>
</RtlPorts>
<RtlPorts>
<name>layer9_out_full_n</name>
<Object>layer9_out</Object>
<Type>pointer</Type>
<Scope></Scope>
<IOProtocol>ap_fifo</IOProtocol>
<IOConfig></IOConfig>
<Dir>in</Dir>
<Bits>1</Bits>
<Attribute>control</Attribute>
</RtlPorts>
<RtlPorts>
<name>layer9_out_write</name>
<Object>layer9_out</Object>
<Type>pointer</Type>
<Scope></Scope>
<IOProtocol>ap_fifo</IOProtocol>
<IOConfig></IOConfig>
<Dir>out</Dir>
<Bits>1</Bits>
<Attribute>control</Attribute>
</RtlPorts>
</InterfaceSummary>

</profile>
